gemini_deepsearch_mcp/__init__.py
gemini_deepsearch_mcp/app.py
gemini_deepsearch_mcp/main.py
gemini_deepsearch_mcp/agent/__init__.py
gemini_deepsearch_mcp/agent/configuration.py
gemini_deepsearch_mcp/agent/graph.py
gemini_deepsearch_mcp/agent/prompts.py
gemini_deepsearch_mcp/agent/state.py
gemini_deepsearch_mcp/agent/tools_and_schemas.py
gemini_deepsearch_mcp/agent/utils.py
gemini_deepsearch_mcp-0.1.5.dist-info/METADATA
gemini_deepsearch_mcp-0.1.5.dist-info/WHEEL
gemini_deepsearch_mcp-0.1.5.dist-info/entry_points.txt
gemini_deepsearch_mcp-0.1.5.dist-info/top_level.txt
gemini_deepsearch_mcp-0.1.5.dist-info/RECORD
