Metadata-Version: 2.4
Name: gemini-deepsearch-mcp
Version: 0.1.5
Summary: Gemini DeepSearch MCP - Automated research agent with Google Gemini models
Author-email: Alex Cong <alexcong@gmail.com>
License: MIT
Project-URL: Homepage, https://github.com/alexcong/gemini-deepsearch-mcp
Project-URL: Repository, https://github.com/alexcong/gemini-deepsearch-mcp
Project-URL: Issues, https://github.com/alexcong/gemini-deepsearch-mcp/issues
Keywords: mcp,gemini,research,ai,langgraph
Requires-Python: >=3.12
Requires-Dist: langgraph>=0.2.6
Requires-Dist: langchain>=0.3.19
Requires-Dist: langchain-google-genai
Requires-Dist: python-dotenv>=1.0.1
Requires-Dist: langgraph-sdk>=0.1.57
Requires-Dist: langgraph-cli
Requires-Dist: langgraph-api
Requires-Dist: fastmcp
Requires-Dist: fastapi
Requires-Dist: google-genai
Requires-Dist: google-ai-generativelanguage>=0.6.18
Provides-Extra: dev
Requires-Dist: mypy>=1.11.1; extra == "dev"
Requires-Dist: ruff>=0.6.1; extra == "dev"
